levicanvas/__init__.py
levicanvas/Canvas.py
levicanvas-1.0.1.dist-info/LICENSE
levicanvas-1.0.1.dist-info/METADATA
levicanvas-1.0.1.dist-info/WHEEL
levicanvas-1.0.1.dist-info/RECORD
