Metadata-Version: 2.3
Name: levicanvas
Version: 1.0.1
Summary: 一个功能强大的图片处理工具箱
Author: a木木
Author-email: mumuwj0001@163.com
Requires-Python: >=3.10
Classifier: Programming Language :: Python :: 3
Classifier: Programming Language :: Python :: 3.10
Classifier: Programming Language :: Python :: 3.11
Requires-Dist: Pillow (>=9.0.0)
Requires-Dist: httpx (>=0.24.0)
Requires-Dist: qrcode (>=7.4.0)
